{"version":1,"resource":"file:///home/yeipi/Github/Tarea/Blog/cliente/src/components/Author.js","entries":[{"id":"LvLY.js","timestamp":1713980436997},{"id":"QsOv.js","timestamp":1713980447037},{"id":"ukKi.js","timestamp":1713980468167},{"id":"c635.js","timestamp":1713981547117},{"id":"RapF.js","timestamp":1713981598567},{"id":"lzwV.js","timestamp":1713981642357},{"id":"53DU.js","timestamp":1713981680760},{"id":"ha80.js","timestamp":1713981715530},{"id":"Y9Yi.js","timestamp":1713982359207},{"id":"wCn7.js","timestamp":1713982408240},{"id":"raRp.js","timestamp":1713982421077},{"id":"6ZD2.js","source":"undoRedo.source","timestamp":1713982430540},{"id":"1rH8.js","timestamp":1713982454380},{"id":"lDVm.js","timestamp":1713982568693},{"id":"QnTn.js","timestamp":1713982595603},{"id":"7b2D.js","timestamp":1713984046627},{"id":"6vMN.js","timestamp":1713984070763},{"id":"xKQv.js","timestamp":1713984090820},{"id":"Q6O0.js","timestamp":1713984111890},{"id":"FzTc.js","timestamp":1713984193853},{"id":"T0z6.js","timestamp":1713984220817},{"id":"wrcw.js","timestamp":1713984232283},{"id":"hk6Y.js","timestamp":1713984299490},{"id":"Od0P.js","timestamp":1713984320163},{"id":"t48R.js","timestamp":1713984516923},{"id":"rAUh.js","source":"undoRedo.source","timestamp":1713984525853}]}